aceofbases/__init__.py
aceofbases/base_editor.py
aceofbases/bed_interval.py
aceofbases/editing_sites.py
aceofbases/generate_target_site_svg.py
aceofbases/gff2bedFiles.py
aceofbases/main.py
aceofbases/off_target.py
aceofbases/pam.py
aceofbases/sequence_methods.py
aceofbases-1.0.0.dist-info/LICENSE
aceofbases-1.0.0.dist-info/METADATA
aceofbases-1.0.0.dist-info/WHEEL
aceofbases-1.0.0.dist-info/entry_points.txt
aceofbases-1.0.0.dist-info/top_level.txt
aceofbases-1.0.0.dist-info/RECORD
