Metadata-Version: 2.1
Name: aceofbases
Version: 1.0.0
Summary: ACEofBASEs, a careful evaluation of BaseEdits
Home-page: https://bitbucket.org/juanlmateo/aceofbases_standalone
Author: Juan L. Mateo
Author-email: mateojuan@uniovi.es
License: UNKNOWN
Project-URL: Bug Tracker, https://bitbucket.org/juanlmateo/aceofbases_standalone/issues
Keywords: CRISPR
Platform: UNKNOWN
Classifier: Environment :: Console
Classifier: Intended Audience :: Science/Research
Classifier: License :: OSI Approved :: MIT License
Requires-Python: >=3.5
License-File: LICENSE
Requires-Dist: bx-python
